mcp_ingest/__init__.py
mcp_ingest/cli.py
mcp_ingest/sdk.py
mcp_ingest/detect/autogen.py
mcp_ingest/detect/base.py
mcp_ingest/detect/crewai.py
mcp_ingest/detect/fastmcp.py
mcp_ingest/detect/langchain.py
mcp_ingest/detect/llamaindex.py
mcp_ingest/detect/raw_mcp.py
mcp_ingest/detect/semantic_kernel.py
mcp_ingest/emit/adapters.py
mcp_ingest/emit/enrich.py
mcp_ingest/emit/index.py
mcp_ingest/emit/manifest.py
mcp_ingest/harvest/repo.py
mcp_ingest/harvest/source.py
mcp_ingest/publishers/static_index.py
mcp_ingest/register/gateway_client.py
mcp_ingest/register/hub_client.py
mcp_ingest/utils/ast_parse.py
mcp_ingest/utils/extractor.py
mcp_ingest/utils/fetch.py
mcp_ingest/utils/git.py
mcp_ingest/utils/github_archive.py
mcp_ingest/utils/github_contents.py
mcp_ingest/utils/http_cache.py
mcp_ingest/utils/idempotency.py
mcp_ingest/utils/io.py
mcp_ingest/utils/jsonschema.py
mcp_ingest/utils/slug.py
mcp_ingest/utils/sse.py
mcp_ingest/utils/temp.py
mcp_ingest/validate/mcp_probe.py
mcp_ingest/validate/sandbox.py
mcp_ingest/validate/sandbox_container.py
mcp_ingest-0.1.1.dist-info/METADATA
mcp_ingest-0.1.1.dist-info/WHEEL
mcp_ingest-0.1.1.dist-info/entry_points.txt
mcp_ingest-0.1.1.dist-info/RECORD
