Metadata-Version: 2.4
Name: mcp-ingest
Version: 0.1.1
Summary: SDK + CLI to describe, validate, and register MCP servers into MatrixHub
Author: MatrixHub Contributors
License: Apache-2.0
Keywords: agents,ingest,matrixhub,mcp,model-context-protocol
Classifier: License :: OSI Approved :: Apache Software License
Classifier: Operating System :: OS Independent
Classifier: Programming Language :: Python :: 3
Classifier: Programming Language :: Python :: 3.11
Requires-Python: <3.13,>=3.11
Requires-Dist: anyio<5,>=3.6
Requires-Dist: httpx<0.29,>=0.24
Requires-Dist: pydantic<3,>=2
Requires-Dist: pyyaml<7.0,>=6.0
Provides-Extra: dev
Requires-Dist: black>=24.0; extra == 'dev'
Requires-Dist: build>=1.0; extra == 'dev'
Requires-Dist: mypy>=1.8; extra == 'dev'
Requires-Dist: pytest-cov>=4.0; extra == 'dev'
Requires-Dist: pytest>=7.0; extra == 'dev'
Requires-Dist: ruff>=0.4; extra == 'dev'
Requires-Dist: twine>=4.0; extra == 'dev'
Requires-Dist: types-pyyaml; extra == 'dev'
Provides-Extra: docs
Requires-Dist: mkdocs-material<10,>=9.5; extra == 'docs'
Requires-Dist: mkdocs-mermaid2-plugin<2,>=1.1; extra == 'docs'
Requires-Dist: mkdocs<2,>=1.5; extra == 'docs'
Requires-Dist: pymdown-extensions<12,>=10; extra == 'docs'
Provides-Extra: harvester
Requires-Dist: fastapi>=0.110; extra == 'harvester'
Requires-Dist: sqlalchemy>=2.0; extra == 'harvester'
Requires-Dist: uvicorn>=0.23; extra == 'harvester'
